{"word": "apothecary", "accent": "/\u0259\u02c8p\u0251\u02d0\u03b8\u0259keri/", "mean_cn": "n. \u836f\u5242\u5e08", "mean_en": "a person who prepared and sold medicines in past times", "sentence": "The apothecary is preparing medicines in his herbal medicine shop.", "sentence_trans": "\u836f\u5242\u5e08\u6b63\u5728\u4ed6\u7684\u836f\u94fa\u91cc\u6293\u836f\u3002", "sentence_phrase": "", "word_etyma": "", "cloze_data": {"syllable": "apothe-cary", "cloze": "apo[th]e-cary", "options": ["tch|chr|sch|sh"], "tips": [["apo[th]ecal", "apo[th]ecial"]]}}