{"word": "foundry", "accent": "/'fa\u028andri/", "mean_cn": "n. \u94f8\u9020\u573a\uff0c\u94f8\u9020\uff0c\u94f8\u9020\u7c7b", "mean_en": "a factory where metal or glass is melted and made into different shapes or objects", "sentence": "Iron is melted and formed into different shapes in this foundry.", "sentence_trans": "\u5728\u8fd9\u4e2a\u94f8\u9020\u5382\u91cc\uff0c\u94c1\u88ab\u878d\u5316\u5e76\u5851\u9020\u6210\u4e0d\u540c\u7684\u5f62\u72b6\u3002", "sentence_phrase": "", "word_etyma": "", "cloze_data": {}}