{"word": "fumble", "accent": "/\u02c8f\u028cmbl/", "mean_cn": "v. \u6478\u7d22\uff0c\u7b28\u62d9\u5730\u505a\uff0c\u6f0f\u7403\uff1b  n. \u6478\u7d22\uff0c\u7b28\u62d9\u7684\u5904\u7406\uff0c\u6f0f\u7403", "mean_en": "to handle something in an awkward or clumsy way", "sentence": "The blind girl fumbles around the room for her boyfriend.", "sentence_trans": "\u5931\u660e\u7684\u5973\u5b69\u5728\u623f\u95f4\u91cc\u6478\u7d22\u7740\u5bfb\u627e\u5979\u7684\u7537\u670b\u53cb\u3002", "sentence_phrase": "", "word_etyma": "", "cloze_data": {"syllable": "fum-ble", "cloze": "fum-[ble]", "options": ["tle|dle|ple|cle|gle|kle"], "tips": [["ca[ble]", "am[ble]"]]}}