{"word": "functionalism", "accent": "/\u02c8f\u028c\u014bk\u0283\u0259n\u0259l\u026az\u0259m/", "mean_cn": "n. \u673a\u80fd\u4e3b\u4e49\uff0c\u673a\u80fd\u5fc3\u7406\u5b66\uff0c\u5b9e\u7528\u7b2c\u4e00\u4e3b\u4e49", "mean_en": "idea that the most important aspect of something, especially the design of a building or piece of furniture, is how it is going to be used or its usefulness", "sentence": "The functionalism of old factories gives them a strange kind of beauty.", "sentence_trans": "\u7834\u65e7\u5de5\u5382\u7684\u673a\u80fd\u4e3b\u4e49\u4e3a\u5b83\u4eec\u5e26\u6765\u4e00\u79cd\u5947\u5999\u7684\u7f8e\u611f\u3002", "sentence_phrase": "functionalism of old factories", "word_etyma": "function\u673a\u80fd \uff0b alism...\u4e3b\u4e49 \u2192 functionalism\u673a\u80fd\u4e3b\u4e49", "cloze_data": {"syllable": "func-tion-al-ism", "cloze": "func-t[ion]-[al]-ism", "options": ["ing|ang|ong|ung", "el|le|nl|ol"], "tips": [["act[ion]", "dat[ion]"], ["[al]", "[al]ba"]]}}