{"word": "haulage", "accent": "/'h\u0254\u02d0l\u026ad\u0292/", "mean_cn": "n. \u8fd0\u8f93\uff0c\u8fd0\u8d39", "mean_en": "the business of transporting goods by road or railway; money charged for this", "sentence": "I work in the haulage industry and transport large amounts of timber.", "sentence_trans": "\b\u6211\u5728\u8fd0\u8f93\u4e1a\u5de5\u4f5c\uff0c\u8d1f\u8d23\u8fd0\u8f93\u5927\u91cf\u6728\u6750\u3002", "sentence_phrase": "", "word_etyma": "haul\u62d6 + age \u2192 haulage\u8fd0\u8f93", "cloze_data": {}}