{"word": "in-house", "accent": "/\u02cc\u026an \u02c8ha\u028as/", "mean_cn": "adj. \uff08\u673a\u6784\uff09\u5185\u90e8\u7684\uff1b  adv. \uff08\u673a\u6784\uff09\u5185\u90e8\u5730\u00a0", "mean_en": "existing or happening within a company or an organization.", "sentence": "This is an in-house meeting, only company members can attend.", "sentence_trans": "\u8fd9\u662f\u4e2a\u5185\u90e8\u4f1a\u8bae\uff0c\u53ea\u6709\u516c\u53f8\u6210\u5458\u624d\u80fd\u53c2\u52a0\u3002", "sentence_phrase": "", "word_etyma": "", "cloze_data": {}}