{"word": "meanwhile", "accent": "/\u02c8mi\u02d0nwa\u026al/", "mean_cn": "adv.\u540c\u65f6\uff0c\u4e0e\u6b64\u540c\u65f6\uff1b  n.\u5176\u95f4", "mean_en": "at or during the same time; in the meantime", "sentence": "The hare decided to take a rest; meanwhile, the tortoise kept moving.", "sentence_trans": "\u5154\u5b50\u51b3\u5b9a\u4f11\u606f\u4e00\u4e0b\uff0c\u4e0e\u6b64\u540c\u65f6\uff0c\u4e4c\u9f9f\u8fd8\u5728\u7ee7\u7eed\u524d\u8fdb\u3002", "sentence_phrase": "", "word_etyma": "mean\u7528\u610f + while\u540c\u65f6 \u2192 meanwhile\u540c\u65f6\uff0c\u5f53\u65f6", "cloze_data": {"syllable": "mean-while", "cloze": "mean-whi[le]", "options": ["al|el|nl|ol"], "tips": [["whi[le]", "handwhi[le]"]]}}