{"word": "oatmeal", "accent": "/\u02c8o\u028atmi\u02d0l/", "mean_cn": "n. \u71d5\u9ea6\u7247\uff0c\u71d5\u9ea6\u7ca5", "mean_en": "a hot breakfast food that is made from oats", "sentence": "Oatmeal is a boring but healthy breakfast made by boiling oats with water.", "sentence_trans": "\u71d5\u9ea6\u7ca5\u662f\u4e00\u79cd\u4ee4\u4eba\u4e4f\u5473\u5374\u5f88\u5065\u5eb7\u7684\u65e9\u9910\uff0c\u52a0\u6c34\u716e\u719f\u71d5\u9ea6\u800c\u6210\u3002", "sentence_phrase": "", "word_etyma": "oat\u71d5\u9ea6 \uff0b meal\u98df\u7269 \u2192 oatmeal\u71d5\u9ea6\u7ca5\uff1b\u71d5\u9ea6\u7247", "cloze_data": {"syllable": "oat-meal", "cloze": "oat-me[al]", "options": ["el|le|nl|ol"], "tips": [["me[al]", "beme[al]"]]}}