{"word": "operator", "accent": "/\u02c8\u0251\u02d0p\u0259re\u026at\u0259r/", "mean_cn": "n.\uff08\u7535\u8bdd\uff09\u63a5\u7ebf\u5458", "mean_en": "a person whose job is to help to connect telephone calls; a person who is in charge of a telephone switchboard", "sentence": "Ask for the operator\u2014she\u2019ll know the right phone number.", "sentence_trans": "\u4f60\u53ef\u4ee5\u8be2\u95ee\u63a5\u7ebf\u5458\uff0c\u5979\u77e5\u9053\u6b63\u786e\u7684\u7535\u8bdd\u53f7\u7801\u3002", "sentence_phrase": "", "word_etyma": "oper\u5de5\u4f5c + ator\u8868\u793a\u505a...\u5de5\u4f5c\u7684\u4eba\u6216\u7269 \u2192 operator\u64cd\u4f5c\u4eba\u5458\uff0c\u63a5\u7ebf\u5458", "cloze_data": {"syllable": "op-e-ra-tor", "cloze": "op-e-r[a]-t[or]", "options": ["e|i|o|u", "ar|er|ir|ur|a"], "tips": [["Ir[a]", "or[a]"], ["t[or]", "fet[or]"]]}}