{"word": "pallet", "accent": "/'p\u00e6l\u0259t/", "mean_cn": "n. \u6258\u76d8\uff0c\u7b80\u964b\u7684\u5c0f\u5e8a", "mean_en": "a heavy wooden or metal base that can be used for moving or storing goods", "sentence": "Place the boxes on the pallet, so that they can be easily transported.", "sentence_trans": "\u628a\u7bb1\u5b50\u653e\u5728\u8fd9\u4e2a\u6258\u76d8\u4e0a\uff0c\u8fd9\u6837\u80fd\u66f4\u65b9\u4fbf\u5730\u8fd0\u8f93\u5b83\u4eec\u3002", "sentence_phrase": "", "word_etyma": "", "cloze_data": {}}