{"word": "pollster", "accent": "/\u02c8po\u028alst\u0259r/", "mean_cn": "n. \u6574\u7406\u6c11\u610f\u6d4b\u9a8c\u7ed3\u679c\u7684\u4eba\uff1b\u6c11\u610f\u6d4b\u9a8c\u4e13\u5bb6\uff0c\u6c11\u610f\u8c03\u67e5\u4eba", "mean_en": "someone who makes questions for a poll, asks questions in a poll, or collects and presents results from a poll", "sentence": "Pollsters find out how most people think about things.", "sentence_trans": "\u6c11\u610f\u6d4b\u9a8c\u4e13\u5bb6\u8c03\u67e5\u5927\u591a\u6570\u4eba\u662f\u5982\u4f55\u770b\u5f85\u4e00\u4e9b\u4e8b\u60c5\u7684\u3002", "sentence_phrase": "", "word_etyma": "poll\u6c11\u610f\u8c03\u67e5 + ster\u8868\u4eba \u2192 pollster\u6c11\u610f\u6d4b\u9a8c\u5bb6", "cloze_data": {"syllable": "poll-ster", "cloze": "p[oll]-ster", "options": ["old|olt|olk|ost"], "tips": [["rep[oll]", "p[oll]"]]}}