{"word": "probate", "accent": "/\u02c8pro\u028abe\u026at/", "mean_cn": "n. \u9057\u5631\u68c0\u9a8c\uff1b  v. \u9057\u5631\u8ba4\u8bc1", "mean_en": "the process of proving in court that the will of a person who has died is valid", "sentence": "After my father's will goes through probate, I will receive my inheritance.", "sentence_trans": "\u7236\u4eb2\u7684\u9057\u5631\u7ecf\u8fc7\u68c0\u9a8c\u4e4b\u540e\uff0c\u6211\u5c31\u53ef\u4ee5\u7ee7\u627f\u9057\u4ea7\u4e86\u3002", "sentence_phrase": "", "word_etyma": "prob\u8bc1\u660e \uff0b ate\u52a8\u8bcd\u540e\u7f00 \u2192 probate\u9057\u5631\u8ba4\u8bc1\uff1b\u5904\u4ee5\u7f13\u5211", "cloze_data": {"syllable": "pro-bate", "cloze": "pro-b[a]te", "options": ["e|i|o|u"], "tips": [["ab[a]te", "deb[a]te"]]}}