{"word": "Rosetta", "accent": "/ro\u02c8z\u025bt\u0259/", "mean_cn": "n.\u7f57\u585e\u5854\uff08\u57ce\u5e02\u540d\uff09", "mean_en": "Rosetta", "sentence": "The Rosetta Stone was the key to understanding some early civilizations.", "sentence_trans": "\u8fd9\u5757\u7f57\u585e\u5854\u77f3\u7891\uff08\u89e3\u91ca\u53e4\u57c3\u53ca\u8c61\u5f62\u6587\u5b57\u7684\u53ef\u9760\u7ebf\u7d22\uff09\u53ef\u4ee5\u5e2e\u6211\u4eec\u4e86\u89e3\u65e9\u671f\u6587\u660e\u3002", "sentence_phrase": "Rosetta Stone", "word_etyma": "", "cloze_data": {"syllable": "Roset-ta", "cloze": "Rosett[a]", "options": ["e|i|o|u"], "tips": [[]]}}