{"word": "shag", "accent": "/\u0283\u00e6\u0261/", "mean_cn": "n. \u7c97\u6bdb\uff0c\u7c97\u70df\u4e1d\uff0c\u84ec\u4e71\u4e00\u56e2\uff1b  v. \u4f7f\u6742\u4e71\uff0c\u4f7f\u84ec\u677e\uff1b  adj. \u6709\u7c97\u6bdb\u7684\uff0c\u84ec\u4e71\u7684", "mean_en": "", "sentence": "The dog's hair is in a shag style; I can barely tell it's head from it's tail.", "sentence_trans": "\u8fd9\u72d7\u7684\u6bdb\u53d1\u5448\u84ec\u4e71\u72b6\u6001\uff0c\u6211\u51e0\u4e4e\u5206\u8fa8\u4e0d\u51fa\u5b83\u7684\u5934\u548c\u5c3e\u5df4\u5728\u54ea\u3002", "sentence_phrase": "in a shag style", "word_etyma": "", "cloze_data": {"syllable": "shag", "cloze": "[sh]ag", "options": ["tch|chr|sch|th"], "tips": [["be[sh]ag", "[sh]agbag"]]}}