{"word": "slay", "accent": "/sle\u026a/", "mean_cn": "v. \u6b8b\u6740\uff0c\uff08\u5927\u89c4\u6a21\uff09\u5c60\u6740\uff0c\u4f7f\u7981\u4e0d\u4f4f\u5927\u7b11", "mean_en": "to kill (someone)", "sentence": "The dragon was slain by the prince on the spot.", "sentence_trans": "\u8fd9\u6761\u9f99\u88ab\u738b\u5b50\u5f53\u573a\u6740\u6b7b\u3002", "sentence_phrase": "", "word_etyma": "", "cloze_data": {"syllable": "slay", "cloze": "sl[ay]", "options": ["aa|ai|ei|aw|ey|a"], "tips": [["sl[ay]er", "sl[ay]ing"]]}}