{"word": "that", "accent": "/\u00f0\u00e6t/", "mean_cn": "pron.\u90a3\uff0c\u90a3\u4e2a\uff1b\u90a3\u8fb9\uff1b  conj.\u5f15\u5bfc\u4ece\u53e5\uff1b  adj.\u90a3\uff0c\u90a3\u4e2a\uff1b  adv.\u90a3\u6837\uff0c\u90a3\u4e48", "mean_en": "", "sentence": "Do you want this book or that one?", "sentence_trans": "\u4f60\u60f3\u8981\u8fd9\u672c\u4e66\u8fd8\u662f\u90a3\u4e00\u672c\uff1f", "sentence_phrase": "", "word_etyma": "", "cloze_data": {"syllable": "that", "cloze": "[th]at", "options": ["tch|chr|sch|sh"], "tips": [["[th]atness"]]}}