{"word": "waybill", "accent": "/'we\u026a\u02ccb\u026al/", "mean_cn": "n. \u8fd0\u8d27\u5355\uff0c\u4e58\u5ba2\u540d\u5355", "mean_en": "a document that shows the details of and instructions relating to goods that are being transported by a company", "sentence": "You must fill in the waybill with an address and phone number when mailing a package.", "sentence_trans": "\u5728\u90ae\u5bc4\u5305\u88f9\u7684\u65f6\u5019\u4f60\u5fc5\u987b\u628a\u5730\u5740\u548c\u7535\u8bdd\u53f7\u7801\u586b\u5199\u5728\u8fd0\u5355\u4e0a\u3002", "sentence_phrase": "", "word_etyma": "", "cloze_data": {}}